grnm.py
clustering/__init__.py
clustering/louvain_clustering.py
dimensionality_reduction/__init__.py
dimensionality_reduction/graph_autoencoder.py
dimensionality_reduction/graph_preprocessing.py
dimensionality_reduction/pca_preprocessing.py
dimensionality_reduction/umap_preprocessing.py
plotting/__init__.py
plotting/generate_heatmap.py
plotting/grn_visualization.py
plotting/module_target_visualization.py
preprocessing/__init__.py
preprocessing/edgeadjacency.py
preprocessing/markgenepre.py
grnm-0.6.dist-info/METADATA
grnm-0.6.dist-info/WHEEL
grnm-0.6.dist-info/top_level.txt
grnm-0.6.dist-info/RECORD
