Metadata-Version: 2.1
Name: grnm
Version: 0.6
Summary: A comprehensive tool for gene regulatory network modeling.
Author: heay
Author-email: hyjd21@gmail.com
License: MIT
Keywords: gene regulatory networks,bioinformatics,graph models,network analysis
Requires-Python: >=3.7
Requires-Dist: numpy (>=1.22.0)
Requires-Dist: pandas (==2.0.3)
Requires-Dist: python-louvain (==0.16)
Requires-Dist: matplotlib (==3.7.2)
Requires-Dist: networkx (==3.2.1)
Requires-Dist: scikit-learn
Requires-Dist: torch (==2.2.1)
Requires-Dist: dgl
Requires-Dist: umap-learn (==0.5.3)
Requires-Dist: seaborn (==0.13.2)
